explainerdashboard/__init__.py
explainerdashboard/cli.py
explainerdashboard/custom.py
explainerdashboard/dashboard_methods.py
explainerdashboard/dashboards.py
explainerdashboard/datasets.py
explainerdashboard/explainer_methods.py
explainerdashboard/explainer_plots.py
explainerdashboard/explainers.py
explainerdashboard/to_html.py
explainerdashboard/dashboard_components/__init__.py
explainerdashboard/dashboard_components/classifier_components.py
explainerdashboard/dashboard_components/composites.py
explainerdashboard/dashboard_components/connectors.py
explainerdashboard/dashboard_components/decisiontree_components.py
explainerdashboard/dashboard_components/overview_components.py
explainerdashboard/dashboard_components/regression_components.py
explainerdashboard/dashboard_components/shap_components.py
explainerdashboard/assets/bootstrap.min.css
explainerdashboard/assets/favicon.ico
explainerdashboard/datasets/titanic_test.csv
explainerdashboard/datasets/titanic_train.csv
explainerdashboard/static/bootstrap.min.css
explainerdashboard/static/bootstrap.min.js
explainerdashboard/static/favicon.ico
explainerdashboard-0.5.4.dist-info/METADATA
explainerdashboard-0.5.4.dist-info/WHEEL
explainerdashboard-0.5.4.dist-info/entry_points.txt
explainerdashboard-0.5.4.dist-info/licenses/LICENSE.txt
explainerdashboard-0.5.4.dist-info/RECORD
