Metadata-Version: 2.4
Name: explainerdashboard
Version: 0.5.4
Summary: Quickly build Explainable AI dashboards that show the inner workings of so-called "blackbox" machine learning models.
Project-URL: Homepage, https://github.com/oegedijk/explainerdashboard
Project-URL: Documentation, https://explainerdashboard.readthedocs.io/
Project-URL: Source Code, https://github.com/oegedijk/explainerdashboard/
Project-URL: Bug Tracker, https://github.com/oegedijk/explainerdashboard/issues
Project-URL: Funding, https://github.com/sponsors/oegedijk
Author-email: Oege Dijk <oegedijk@gmail.com>
License: Copyright (c) 2019 Oege Dijk
License-File: LICENSE.txt
Keywords: dash,explainability,feature importances,machine learning,shap
Classifier: Development Status :: 3 - Alpha
Classifier: Environment :: Web Environment
Classifier: Framework :: Dash
Classifier: Framework :: Flask
Classifier: Intended Audience :: Developers
Classifier: Intended Audience :: Education
Classifier: License :: OSI Approved :: MIT License
Classifier: Programming Language :: Python :: 3
Classifier: Programming Language :: Python :: 3.10
Classifier: Programming Language :: Python :: 3.11
Classifier: Programming Language :: Python :: 3.12
Classifier: Programming Language :: Python :: 3.13
Classifier: Topic :: Scientific/Engineering :: Artificial Intelligence
Requires-Python: >=3.10
Requires-Dist: click
Requires-Dist: dash-auth
Requires-Dist: dash-bootstrap-components<3.0,>=1.6.0
Requires-Dist: dash>=3.0.4
Requires-Dist: dtreeviz>=2.1
Requires-Dist: flask-simplelogin
Requires-Dist: flask-wtf>=1.1
Requires-Dist: graphviz>=0.18.2
Requires-Dist: joblib
Requires-Dist: jupyter-dash>=0.4.1
Requires-Dist: numpy; python_version < '3.11'
Requires-Dist: numpy<2.4; python_version >= '3.11'
Requires-Dist: oyaml
Requires-Dist: pandas>=1.1
Requires-Dist: plotly>=5.0
Requires-Dist: scikit-learn>=1.1
Requires-Dist: shap>=0.42.1
Requires-Dist: waitress
Provides-Extra: docs
Requires-Dist: sphinx-autodoc-typehints; extra == 'docs'
Requires-Dist: sphinx-rtd-theme; extra == 'docs'
Requires-Dist: sphinx>=4.0; extra == 'docs'
Provides-Extra: test
Requires-Dist: catboost; extra == 'test'
Requires-Dist: dash[testing]; extra == 'test'
Requires-Dist: dill; extra == 'test'
Requires-Dist: lightgbm; extra == 'test'
Requires-Dist: pytest; extra == 'test'
Requires-Dist: pytest-console-scripts; extra == 'test'
Requires-Dist: pytest-cov; extra == 'test'
Requires-Dist: ruff; extra == 'test'
Requires-Dist: skorch; (sys_platform != 'darwin' or platform_machine != 'x86_64') and extra == 'test'
Requires-Dist: torch; (sys_platform != 'darwin' or platform_machine != 'x86_64') and extra == 'test'
Requires-Dist: webdriver-manager; extra == 'test'
Requires-Dist: xgboost<3.1,>=2.0.0; extra == 'test'
